{
  "generated_at": "2025-12-08 05:38:15",
  "base_datetime": "2025-12-08 01:00:00",
  "data_staleness_hours": 4.6,
  "model_version": "gpu_enhanced_v1",
  "model_performance": {
    "test_mae": 32.43,
    "baseline_mae": 32.2
  },
  "forecasts": [
    {
      "horizon": 1,
      "target_datetime": "2025-12-08 02:00:00",
      "predicted_cmg": 58.71,
      "real_time_offset": -3.6,
      "is_valid_forecast": false,
      "zero_probability": 0.0575,
      "zero_probability_raw": 0.2588,
      "decision_threshold": 0.3636,
      "value_prediction": 58.71,
      "confidence_interval": {
        "lower_10th": 35.93,
        "median": 58.71,
        "upper_90th": 68.01
      }
    },
    {
      "horizon": 2,
      "target_datetime": "2025-12-08 03:00:00",
      "predicted_cmg": 55.9,
      "real_time_offset": -2.6,
      "is_valid_forecast": false,
      "zero_probability": 0.0633,
      "zero_probability_raw": 0.2659,
      "decision_threshold": 0.3651,
      "value_prediction": 55.9,
      "confidence_interval": {
        "lower_10th": 35.58,
        "median": 55.9,
        "upper_90th": 62.27
      }
    },
    {
      "horizon": 3,
      "target_datetime": "2025-12-08 04:00:00",
      "predicted_cmg": 56.87,
      "real_time_offset": -1.6,
      "is_valid_forecast": false,
      "zero_probability": 0.0922,
      "zero_probability_raw": 0.2916,
      "decision_threshold": 0.3676,
      "value_prediction": 56.87,
      "confidence_interval": {
        "lower_10th": 31.26,
        "median": 56.87,
        "upper_90th": 57.33
      }
    },
    {
      "horizon": 4,
      "target_datetime": "2025-12-08 05:00:00",
      "predicted_cmg": 57.11,
      "real_time_offset": -0.6,
      "is_valid_forecast": false,
      "zero_probability": 0.0659,
      "zero_probability_raw": 0.2723,
      "decision_threshold": 0.3691,
      "value_prediction": 57.11,
      "confidence_interval": {
        "lower_10th": 27.52,
        "median": 57.11,
        "upper_90th": 64.56
      }
    },
    {
      "horizon": 5,
      "target_datetime": "2025-12-08 06:00:00",
      "predicted_cmg": 57.54,
      "real_time_offset": 0.4,
      "is_valid_forecast": true,
      "zero_probability": 0.0726,
      "zero_probability_raw": 0.2806,
      "decision_threshold": 0.3703,
      "value_prediction": 57.54,
      "confidence_interval": {
        "lower_10th": 34.76,
        "median": 57.54,
        "upper_90th": 68.68
      }
    },
    {
      "horizon": 6,
      "target_datetime": "2025-12-08 07:00:00",
      "predicted_cmg": 61.08,
      "real_time_offset": 1.4,
      "is_valid_forecast": true,
      "zero_probability": 0.1018,
      "zero_probability_raw": 0.3051,
      "decision_threshold": 0.3706,
      "value_prediction": 61.08,
      "confidence_interval": {
        "lower_10th": 28.99,
        "median": 61.08,
        "upper_90th": 66.5
      }
    },
    {
      "horizon": 7,
      "target_datetime": "2025-12-08 08:00:00",
      "predicted_cmg": 52.53,
      "real_time_offset": 2.4,
      "is_valid_forecast": true,
      "zero_probability": 0.1979,
      "zero_probability_raw": 0.3571,
      "decision_threshold": 0.3707,
      "value_prediction": 52.53,
      "confidence_interval": {
        "lower_10th": 27.72,
        "median": 52.53,
        "upper_90th": 73.48
      }
    },
    {
      "horizon": 8,
      "target_datetime": "2025-12-08 09:00:00",
      "predicted_cmg": 0,
      "real_time_offset": 3.4,
      "is_valid_forecast": true,
      "zero_probability": 0.4187,
      "zero_probability_raw": 0.433,
      "decision_threshold": 0.3703,
      "value_prediction": 46.71,
      "confidence_interval": {
        "lower_10th": 24.06,
        "median": 46.71,
        "upper_90th": 85.28
      }
    },
    {
      "horizon": 9,
      "target_datetime": "2025-12-08 10:00:00",
      "predicted_cmg": 62.82,
      "real_time_offset": 4.4,
      "is_valid_forecast": true,
      "zero_probability": 0.3335,
      "zero_probability_raw": 0.4081,
      "decision_threshold": 0.3704,
      "value_prediction": 62.82,
      "confidence_interval": {
        "lower_10th": 25.03,
        "median": 62.82,
        "upper_90th": 132.88
      }
    },
    {
      "horizon": 10,
      "target_datetime": "2025-12-08 11:00:00",
      "predicted_cmg": 0,
      "real_time_offset": 5.4,
      "is_valid_forecast": true,
      "zero_probability": 0.44,
      "zero_probability_raw": 0.4402,
      "decision_threshold": 0.3701,
      "value_prediction": 59.31,
      "confidence_interval": {
        "lower_10th": 25.99,
        "median": 59.31,
        "upper_90th": 137.05
      }
    },
    {
      "horizon": 11,
      "target_datetime": "2025-12-08 12:00:00",
      "predicted_cmg": 74.88,
      "real_time_offset": 6.4,
      "is_valid_forecast": true,
      "zero_probability": 0.2912,
      "zero_probability_raw": 0.3935,
      "decision_threshold": 0.3693,
      "value_prediction": 74.88,
      "confidence_interval": {
        "lower_10th": 28.28,
        "median": 74.88,
        "upper_90th": 136.08
      }
    },
    {
      "horizon": 12,
      "target_datetime": "2025-12-08 13:00:00",
      "predicted_cmg": 0,
      "real_time_offset": 7.4,
      "is_valid_forecast": true,
      "zero_probability": 0.6444,
      "zero_probability_raw": 0.498,
      "decision_threshold": 0.3693,
      "value_prediction": 86.66,
      "confidence_interval": {
        "lower_10th": 26.47,
        "median": 86.66,
        "upper_90th": 142.6
      }
    },
    {
      "horizon": 13,
      "target_datetime": "2025-12-08 14:00:00",
      "predicted_cmg": 89.7,
      "real_time_offset": 8.4,
      "is_valid_forecast": true,
      "zero_probability": 0.3676,
      "zero_probability_raw": 0.4135,
      "decision_threshold": 0.3695,
      "value_prediction": 89.7,
      "confidence_interval": {
        "lower_10th": 26.34,
        "median": 89.7,
        "upper_90th": 139.04
      }
    },
    {
      "horizon": 14,
      "target_datetime": "2025-12-08 15:00:00",
      "predicted_cmg": 0,
      "real_time_offset": 9.4,
      "is_valid_forecast": true,
      "zero_probability": 0.4902,
      "zero_probability_raw": 0.446,
      "decision_threshold": 0.3695,
      "value_prediction": 78.5,
      "confidence_interval": {
        "lower_10th": 26.98,
        "median": 78.5,
        "upper_90th": 132.98
      }
    },
    {
      "horizon": 15,
      "target_datetime": "2025-12-08 16:00:00",
      "predicted_cmg": 81.48,
      "real_time_offset": 10.4,
      "is_valid_forecast": true,
      "zero_probability": 0.2832,
      "zero_probability_raw": 0.3795,
      "decision_threshold": 0.3694,
      "value_prediction": 81.48,
      "confidence_interval": {
        "lower_10th": 29.67,
        "median": 81.48,
        "upper_90th": 118.09
      }
    },
    {
      "horizon": 16,
      "target_datetime": "2025-12-08 17:00:00",
      "predicted_cmg": 0,
      "real_time_offset": 11.4,
      "is_valid_forecast": true,
      "zero_probability": 0.4067,
      "zero_probability_raw": 0.4137,
      "decision_threshold": 0.3688,
      "value_prediction": 63.57,
      "confidence_interval": {
        "lower_10th": 25.72,
        "median": 63.57,
        "upper_90th": 115.5
      }
    },
    {
      "horizon": 17,
      "target_datetime": "2025-12-08 18:00:00",
      "predicted_cmg": 69.69,
      "real_time_offset": 12.4,
      "is_valid_forecast": true,
      "zero_probability": 0.3108,
      "zero_probability_raw": 0.3802,
      "decision_threshold": 0.3685,
      "value_prediction": 69.69,
      "confidence_interval": {
        "lower_10th": 24.71,
        "median": 69.69,
        "upper_90th": 95.4
      }
    },
    {
      "horizon": 18,
      "target_datetime": "2025-12-08 19:00:00",
      "predicted_cmg": 0,
      "real_time_offset": 13.4,
      "is_valid_forecast": true,
      "zero_probability": 0.4268,
      "zero_probability_raw": 0.4109,
      "decision_threshold": 0.3681,
      "value_prediction": 68.16,
      "confidence_interval": {
        "lower_10th": 24.53,
        "median": 68.16,
        "upper_90th": 97.03
      }
    },
    {
      "horizon": 19,
      "target_datetime": "2025-12-08 20:00:00",
      "predicted_cmg": 63.15,
      "real_time_offset": 14.4,
      "is_valid_forecast": true,
      "zero_probability": 0.2778,
      "zero_probability_raw": 0.3617,
      "decision_threshold": 0.3686,
      "value_prediction": 63.15,
      "confidence_interval": {
        "lower_10th": 25.58,
        "median": 63.15,
        "upper_90th": 86.4
      }
    },
    {
      "horizon": 20,
      "target_datetime": "2025-12-08 21:00:00",
      "predicted_cmg": 73.2,
      "real_time_offset": 15.4,
      "is_valid_forecast": true,
      "zero_probability": 0.2747,
      "zero_probability_raw": 0.3575,
      "decision_threshold": 0.3682,
      "value_prediction": 73.2,
      "confidence_interval": {
        "lower_10th": 28.89,
        "median": 73.2,
        "upper_90th": 95.9
      }
    },
    {
      "horizon": 21,
      "target_datetime": "2025-12-08 22:00:00",
      "predicted_cmg": 71.56,
      "real_time_offset": 16.4,
      "is_valid_forecast": true,
      "zero_probability": 0.0528,
      "zero_probability_raw": 0.2398,
      "decision_threshold": 0.368,
      "value_prediction": 71.56,
      "confidence_interval": {
        "lower_10th": 40.49,
        "median": 71.56,
        "upper_90th": 89.34
      }
    },
    {
      "horizon": 22,
      "target_datetime": "2025-12-08 23:00:00",
      "predicted_cmg": 70.88,
      "real_time_offset": 17.4,
      "is_valid_forecast": true,
      "zero_probability": 0.0708,
      "zero_probability_raw": 0.2554,
      "decision_threshold": 0.368,
      "value_prediction": 70.88,
      "confidence_interval": {
        "lower_10th": 41.42,
        "median": 70.88,
        "upper_90th": 84.65
      }
    },
    {
      "horizon": 23,
      "target_datetime": "2025-12-09 00:00:00",
      "predicted_cmg": 66.26,
      "real_time_offset": 18.4,
      "is_valid_forecast": true,
      "zero_probability": 0.2665,
      "zero_probability_raw": 0.3501,
      "decision_threshold": 0.3615,
      "value_prediction": 66.26,
      "confidence_interval": {
        "lower_10th": 36.76,
        "median": 66.26,
        "upper_90th": 76.55
      }
    },
    {
      "horizon": 24,
      "target_datetime": "2025-12-09 01:00:00",
      "predicted_cmg": 63.72,
      "real_time_offset": 19.4,
      "is_valid_forecast": true,
      "zero_probability": 0.0419,
      "zero_probability_raw": 0.2255,
      "decision_threshold": 0.3621,
      "value_prediction": 63.72,
      "confidence_interval": {
        "lower_10th": 31.45,
        "median": 63.72,
        "upper_90th": 68.82
      }
    }
  ]
}