{
  "generated_at": "2025-11-20 21:33:27",
  "base_datetime": "2025-11-20 17:00:00",
  "data_staleness_hours": 4.6,
  "model_version": "gpu_enhanced_v1",
  "model_performance": {
    "test_mae": 32.43,
    "baseline_mae": 32.2
  },
  "forecasts": [
    {
      "horizon": 1,
      "target_datetime": "2025-11-20 18:00:00",
      "predicted_cmg": 61.94,
      "real_time_offset": -3.6,
      "is_valid_forecast": false,
      "zero_probability": 0.0314,
      "zero_probability_raw": 0.2162,
      "decision_threshold": 0.3685,
      "value_prediction": 61.94,
      "confidence_interval": {
        "lower_10th": 35.22,
        "median": 61.94,
        "upper_90th": 115.75
      }
    },
    {
      "horizon": 2,
      "target_datetime": "2025-11-20 19:00:00",
      "predicted_cmg": 65.62,
      "real_time_offset": -2.6,
      "is_valid_forecast": false,
      "zero_probability": 0.0454,
      "zero_probability_raw": 0.2327,
      "decision_threshold": 0.3681,
      "value_prediction": 65.62,
      "confidence_interval": {
        "lower_10th": 37.15,
        "median": 65.62,
        "upper_90th": 129.87
      }
    },
    {
      "horizon": 3,
      "target_datetime": "2025-11-20 20:00:00",
      "predicted_cmg": 77.5,
      "real_time_offset": -1.6,
      "is_valid_forecast": false,
      "zero_probability": 0.0422,
      "zero_probability_raw": 0.226,
      "decision_threshold": 0.3686,
      "value_prediction": 77.5,
      "confidence_interval": {
        "lower_10th": 34.95,
        "median": 77.5,
        "upper_90th": 150.38
      }
    },
    {
      "horizon": 4,
      "target_datetime": "2025-11-20 21:00:00",
      "predicted_cmg": 82.02,
      "real_time_offset": -0.6,
      "is_valid_forecast": false,
      "zero_probability": 0.0577,
      "zero_probability_raw": 0.2406,
      "decision_threshold": 0.3682,
      "value_prediction": 82.02,
      "confidence_interval": {
        "lower_10th": 41.51,
        "median": 82.02,
        "upper_90th": 160.86
      }
    },
    {
      "horizon": 5,
      "target_datetime": "2025-11-20 22:00:00",
      "predicted_cmg": 81.33,
      "real_time_offset": 0.4,
      "is_valid_forecast": true,
      "zero_probability": 0.0258,
      "zero_probability_raw": 0.1973,
      "decision_threshold": 0.368,
      "value_prediction": 81.33,
      "confidence_interval": {
        "lower_10th": 43.91,
        "median": 81.33,
        "upper_90th": 152.75
      }
    },
    {
      "horizon": 6,
      "target_datetime": "2025-11-20 23:00:00",
      "predicted_cmg": 72.71,
      "real_time_offset": 1.4,
      "is_valid_forecast": true,
      "zero_probability": 0.0865,
      "zero_probability_raw": 0.2612,
      "decision_threshold": 0.368,
      "value_prediction": 72.71,
      "confidence_interval": {
        "lower_10th": 43.81,
        "median": 72.71,
        "upper_90th": 134.87
      }
    },
    {
      "horizon": 7,
      "target_datetime": "2025-11-21 00:00:00",
      "predicted_cmg": 70.81,
      "real_time_offset": 2.4,
      "is_valid_forecast": true,
      "zero_probability": 0.2348,
      "zero_probability_raw": 0.3315,
      "decision_threshold": 0.3615,
      "value_prediction": 70.81,
      "confidence_interval": {
        "lower_10th": 41.92,
        "median": 70.81,
        "upper_90th": 114.7
      }
    },
    {
      "horizon": 8,
      "target_datetime": "2025-11-21 01:00:00",
      "predicted_cmg": 69.69,
      "real_time_offset": 3.4,
      "is_valid_forecast": true,
      "zero_probability": 0.2949,
      "zero_probability_raw": 0.3519,
      "decision_threshold": 0.3621,
      "value_prediction": 69.69,
      "confidence_interval": {
        "lower_10th": 31.07,
        "median": 69.69,
        "upper_90th": 92.39
      }
    },
    {
      "horizon": 9,
      "target_datetime": "2025-11-21 02:00:00",
      "predicted_cmg": 64.21,
      "real_time_offset": 4.4,
      "is_valid_forecast": true,
      "zero_probability": 0.1798,
      "zero_probability_raw": 0.3112,
      "decision_threshold": 0.3636,
      "value_prediction": 64.21,
      "confidence_interval": {
        "lower_10th": 36.82,
        "median": 64.21,
        "upper_90th": 85.64
      }
    },
    {
      "horizon": 10,
      "target_datetime": "2025-11-21 03:00:00",
      "predicted_cmg": 63.75,
      "real_time_offset": 5.4,
      "is_valid_forecast": true,
      "zero_probability": 0.2249,
      "zero_probability_raw": 0.3305,
      "decision_threshold": 0.3651,
      "value_prediction": 63.75,
      "confidence_interval": {
        "lower_10th": 30.93,
        "median": 63.75,
        "upper_90th": 72.07
      }
    },
    {
      "horizon": 11,
      "target_datetime": "2025-11-21 04:00:00",
      "predicted_cmg": 69.61,
      "real_time_offset": 6.4,
      "is_valid_forecast": true,
      "zero_probability": 0.0872,
      "zero_probability_raw": 0.2651,
      "decision_threshold": 0.3676,
      "value_prediction": 69.61,
      "confidence_interval": {
        "lower_10th": 38.55,
        "median": 69.61,
        "upper_90th": 95.93
      }
    },
    {
      "horizon": 12,
      "target_datetime": "2025-11-21 05:00:00",
      "predicted_cmg": 0,
      "real_time_offset": 7.4,
      "is_valid_forecast": true,
      "zero_probability": 0.4333,
      "zero_probability_raw": 0.4004,
      "decision_threshold": 0.3691,
      "value_prediction": 74.6,
      "confidence_interval": {
        "lower_10th": 40.17,
        "median": 74.6,
        "upper_90th": 97.2
      }
    },
    {
      "horizon": 13,
      "target_datetime": "2025-11-21 06:00:00",
      "predicted_cmg": 79.36,
      "real_time_offset": 8.4,
      "is_valid_forecast": true,
      "zero_probability": 0.2263,
      "zero_probability_raw": 0.338,
      "decision_threshold": 0.3703,
      "value_prediction": 79.36,
      "confidence_interval": {
        "lower_10th": 38.92,
        "median": 79.36,
        "upper_90th": 86.63
      }
    },
    {
      "horizon": 14,
      "target_datetime": "2025-11-21 07:00:00",
      "predicted_cmg": 75.83,
      "real_time_offset": 9.4,
      "is_valid_forecast": true,
      "zero_probability": 0.2033,
      "zero_probability_raw": 0.3315,
      "decision_threshold": 0.3706,
      "value_prediction": 75.83,
      "confidence_interval": {
        "lower_10th": 40.13,
        "median": 75.83,
        "upper_90th": 105.73
      }
    },
    {
      "horizon": 15,
      "target_datetime": "2025-11-21 08:00:00",
      "predicted_cmg": 62.31,
      "real_time_offset": 10.4,
      "is_valid_forecast": true,
      "zero_probability": 0.0681,
      "zero_probability_raw": 0.2581,
      "decision_threshold": 0.3707,
      "value_prediction": 62.31,
      "confidence_interval": {
        "lower_10th": 32.48,
        "median": 62.31,
        "upper_90th": 95.35
      }
    },
    {
      "horizon": 16,
      "target_datetime": "2025-11-21 09:00:00",
      "predicted_cmg": 63.56,
      "real_time_offset": 11.4,
      "is_valid_forecast": true,
      "zero_probability": 0.2879,
      "zero_probability_raw": 0.3655,
      "decision_threshold": 0.3703,
      "value_prediction": 63.56,
      "confidence_interval": {
        "lower_10th": 30.24,
        "median": 63.56,
        "upper_90th": 100.32
      }
    },
    {
      "horizon": 17,
      "target_datetime": "2025-11-21 10:00:00",
      "predicted_cmg": 71.8,
      "real_time_offset": 12.4,
      "is_valid_forecast": true,
      "zero_probability": 0.3553,
      "zero_probability_raw": 0.3875,
      "decision_threshold": 0.3704,
      "value_prediction": 71.8,
      "confidence_interval": {
        "lower_10th": 18.64,
        "median": 71.8,
        "upper_90th": 137.59
      }
    },
    {
      "horizon": 18,
      "target_datetime": "2025-11-21 11:00:00",
      "predicted_cmg": 66.86,
      "real_time_offset": 13.4,
      "is_valid_forecast": true,
      "zero_probability": 0.2879,
      "zero_probability_raw": 0.3664,
      "decision_threshold": 0.3701,
      "value_prediction": 66.86,
      "confidence_interval": {
        "lower_10th": 28.77,
        "median": 66.86,
        "upper_90th": 155.42
      }
    },
    {
      "horizon": 19,
      "target_datetime": "2025-11-21 12:00:00",
      "predicted_cmg": 73.27,
      "real_time_offset": 14.4,
      "is_valid_forecast": true,
      "zero_probability": 0.3629,
      "zero_probability_raw": 0.389,
      "decision_threshold": 0.3693,
      "value_prediction": 73.27,
      "confidence_interval": {
        "lower_10th": 34.46,
        "median": 73.27,
        "upper_90th": 147.77
      }
    },
    {
      "horizon": 20,
      "target_datetime": "2025-11-21 13:00:00",
      "predicted_cmg": 62.01,
      "real_time_offset": 15.4,
      "is_valid_forecast": true,
      "zero_probability": 0.3324,
      "zero_probability_raw": 0.378,
      "decision_threshold": 0.3693,
      "value_prediction": 62.01,
      "confidence_interval": {
        "lower_10th": 33.01,
        "median": 62.01,
        "upper_90th": 142.37
      }
    },
    {
      "horizon": 21,
      "target_datetime": "2025-11-21 14:00:00",
      "predicted_cmg": 64.6,
      "real_time_offset": 16.4,
      "is_valid_forecast": true,
      "zero_probability": 0.2261,
      "zero_probability_raw": 0.3399,
      "decision_threshold": 0.3695,
      "value_prediction": 64.6,
      "confidence_interval": {
        "lower_10th": 30.63,
        "median": 64.6,
        "upper_90th": 112.07
      }
    },
    {
      "horizon": 22,
      "target_datetime": "2025-11-21 15:00:00",
      "predicted_cmg": 63.19,
      "real_time_offset": 17.4,
      "is_valid_forecast": true,
      "zero_probability": 0.1882,
      "zero_probability_raw": 0.3219,
      "decision_threshold": 0.3695,
      "value_prediction": 63.19,
      "confidence_interval": {
        "lower_10th": 29.6,
        "median": 63.19,
        "upper_90th": 95.65
      }
    },
    {
      "horizon": 23,
      "target_datetime": "2025-11-21 16:00:00",
      "predicted_cmg": 0,
      "real_time_offset": 18.4,
      "is_valid_forecast": true,
      "zero_probability": 0.5861,
      "zero_probability_raw": 0.4416,
      "decision_threshold": 0.3694,
      "value_prediction": 56.93,
      "confidence_interval": {
        "lower_10th": 32.76,
        "median": 56.93,
        "upper_90th": 102.62
      }
    },
    {
      "horizon": 24,
      "target_datetime": "2025-11-21 17:00:00",
      "predicted_cmg": 59.53,
      "real_time_offset": 19.4,
      "is_valid_forecast": true,
      "zero_probability": 0.2085,
      "zero_probability_raw": 0.3227,
      "decision_threshold": 0.3688,
      "value_prediction": 59.53,
      "confidence_interval": {
        "lower_10th": 25.69,
        "median": 59.53,
        "upper_90th": 95.77
      }
    }
  ]
}