{
  "generated_at": "2026-04-02 09:17:09",
  "base_datetime": "2026-04-02 05:00:00",
  "data_staleness_hours": 4.3,
  "model_version": "gpu_enhanced_v1",
  "model_performance": {
    "test_mae": 32.43,
    "baseline_mae": 32.2
  },
  "forecasts": [
    {
      "horizon": 1,
      "target_datetime": "2026-04-02 06:00:00",
      "predicted_cmg": 54.93,
      "real_time_offset": -3.3,
      "is_valid_forecast": false,
      "zero_probability": 0.0132,
      "zero_probability_raw": 0.1962,
      "decision_threshold": 0.3703,
      "value_prediction": 54.93,
      "confidence_interval": {
        "lower_10th": 40.11,
        "median": 54.93,
        "upper_90th": 68.69
      }
    },
    {
      "horizon": 2,
      "target_datetime": "2026-04-02 07:00:00",
      "predicted_cmg": 50.12,
      "real_time_offset": -2.3,
      "is_valid_forecast": false,
      "zero_probability": 0.05,
      "zero_probability_raw": 0.2689,
      "decision_threshold": 0.3706,
      "value_prediction": 50.12,
      "confidence_interval": {
        "lower_10th": 35.72,
        "median": 50.12,
        "upper_90th": 72.29
      }
    },
    {
      "horizon": 3,
      "target_datetime": "2026-04-02 08:00:00",
      "predicted_cmg": 48.36,
      "real_time_offset": -1.3,
      "is_valid_forecast": false,
      "zero_probability": 0.1703,
      "zero_probability_raw": 0.3554,
      "decision_threshold": 0.3707,
      "value_prediction": 48.36,
      "confidence_interval": {
        "lower_10th": 24.54,
        "median": 48.36,
        "upper_90th": 77.19
      }
    },
    {
      "horizon": 4,
      "target_datetime": "2026-04-02 09:00:00",
      "predicted_cmg": 0,
      "real_time_offset": -0.3,
      "is_valid_forecast": false,
      "zero_probability": 0.503,
      "zero_probability_raw": 0.4689,
      "decision_threshold": 0.3703,
      "value_prediction": 46.87,
      "confidence_interval": {
        "lower_10th": 26.4,
        "median": 46.87,
        "upper_90th": 81.53
      }
    },
    {
      "horizon": 5,
      "target_datetime": "2026-04-02 10:00:00",
      "predicted_cmg": 0,
      "real_time_offset": 0.7,
      "is_valid_forecast": true,
      "zero_probability": 0.5229,
      "zero_probability_raw": 0.4755,
      "decision_threshold": 0.3704,
      "value_prediction": 56.35,
      "confidence_interval": {
        "lower_10th": 30.75,
        "median": 56.35,
        "upper_90th": 81.87
      }
    },
    {
      "horizon": 6,
      "target_datetime": "2026-04-02 11:00:00",
      "predicted_cmg": 0,
      "real_time_offset": 1.7,
      "is_valid_forecast": true,
      "zero_probability": 0.5123,
      "zero_probability_raw": 0.4725,
      "decision_threshold": 0.3701,
      "value_prediction": 54.07,
      "confidence_interval": {
        "lower_10th": 33.84,
        "median": 54.07,
        "upper_90th": 91.93
      }
    },
    {
      "horizon": 7,
      "target_datetime": "2026-04-02 12:00:00",
      "predicted_cmg": 0,
      "real_time_offset": 2.7,
      "is_valid_forecast": true,
      "zero_probability": 0.5256,
      "zero_probability_raw": 0.4755,
      "decision_threshold": 0.3693,
      "value_prediction": 60.91,
      "confidence_interval": {
        "lower_10th": 29.3,
        "median": 60.91,
        "upper_90th": 105.51
      }
    },
    {
      "horizon": 8,
      "target_datetime": "2026-04-02 13:00:00",
      "predicted_cmg": 0,
      "real_time_offset": 3.7,
      "is_valid_forecast": true,
      "zero_probability": 0.5723,
      "zero_probability_raw": 0.4874,
      "decision_threshold": 0.3693,
      "value_prediction": 59.97,
      "confidence_interval": {
        "lower_10th": 30.82,
        "median": 59.97,
        "upper_90th": 116.6
      }
    },
    {
      "horizon": 9,
      "target_datetime": "2026-04-02 14:00:00",
      "predicted_cmg": 0,
      "real_time_offset": 4.7,
      "is_valid_forecast": true,
      "zero_probability": 0.5057,
      "zero_probability_raw": 0.4652,
      "decision_threshold": 0.3695,
      "value_prediction": 65.73,
      "confidence_interval": {
        "lower_10th": 24.08,
        "median": 65.73,
        "upper_90th": 122.51
      }
    },
    {
      "horizon": 10,
      "target_datetime": "2026-04-02 15:00:00",
      "predicted_cmg": 0,
      "real_time_offset": 5.7,
      "is_valid_forecast": true,
      "zero_probability": 0.5431,
      "zero_probability_raw": 0.4726,
      "decision_threshold": 0.3695,
      "value_prediction": 69.4,
      "confidence_interval": {
        "lower_10th": 25.77,
        "median": 69.4,
        "upper_90th": 111.76
      }
    },
    {
      "horizon": 11,
      "target_datetime": "2026-04-02 16:00:00",
      "predicted_cmg": 0,
      "real_time_offset": 6.7,
      "is_valid_forecast": true,
      "zero_probability": 0.5826,
      "zero_probability_raw": 0.4803,
      "decision_threshold": 0.3694,
      "value_prediction": 67.57,
      "confidence_interval": {
        "lower_10th": 31.22,
        "median": 67.57,
        "upper_90th": 117.35
      }
    },
    {
      "horizon": 12,
      "target_datetime": "2026-04-02 17:00:00",
      "predicted_cmg": 0,
      "real_time_offset": 7.7,
      "is_valid_forecast": true,
      "zero_probability": 0.7053,
      "zero_probability_raw": 0.5151,
      "decision_threshold": 0.3688,
      "value_prediction": 59.32,
      "confidence_interval": {
        "lower_10th": 17.29,
        "median": 59.32,
        "upper_90th": 112.92
      }
    },
    {
      "horizon": 13,
      "target_datetime": "2026-04-02 18:00:00",
      "predicted_cmg": 73.19,
      "real_time_offset": 8.7,
      "is_valid_forecast": true,
      "zero_probability": 0.2303,
      "zero_probability_raw": 0.3631,
      "decision_threshold": 0.3685,
      "value_prediction": 73.19,
      "confidence_interval": {
        "lower_10th": 25.29,
        "median": 73.19,
        "upper_90th": 78.77
      }
    },
    {
      "horizon": 14,
      "target_datetime": "2026-04-02 19:00:00",
      "predicted_cmg": 68.89,
      "real_time_offset": 9.7,
      "is_valid_forecast": true,
      "zero_probability": 0.0992,
      "zero_probability_raw": 0.2952,
      "decision_threshold": 0.3681,
      "value_prediction": 68.89,
      "confidence_interval": {
        "lower_10th": 37.95,
        "median": 68.89,
        "upper_90th": 81.97
      }
    },
    {
      "horizon": 15,
      "target_datetime": "2026-04-02 20:00:00",
      "predicted_cmg": 74.08,
      "real_time_offset": 10.7,
      "is_valid_forecast": true,
      "zero_probability": 0.012,
      "zero_probability_raw": 0.1782,
      "decision_threshold": 0.3686,
      "value_prediction": 74.08,
      "confidence_interval": {
        "lower_10th": 40.34,
        "median": 74.08,
        "upper_90th": 81.71
      }
    },
    {
      "horizon": 16,
      "target_datetime": "2026-04-02 21:00:00",
      "predicted_cmg": 70.81,
      "real_time_offset": 11.7,
      "is_valid_forecast": true,
      "zero_probability": 0.0364,
      "zero_probability_raw": 0.2296,
      "decision_threshold": 0.3682,
      "value_prediction": 70.81,
      "confidence_interval": {
        "lower_10th": 43.76,
        "median": 70.81,
        "upper_90th": 83.47
      }
    },
    {
      "horizon": 17,
      "target_datetime": "2026-04-02 22:00:00",
      "predicted_cmg": 64.53,
      "real_time_offset": 12.7,
      "is_valid_forecast": true,
      "zero_probability": 0.0609,
      "zero_probability_raw": 0.2566,
      "decision_threshold": 0.368,
      "value_prediction": 64.53,
      "confidence_interval": {
        "lower_10th": 41.57,
        "median": 64.53,
        "upper_90th": 72.81
      }
    },
    {
      "horizon": 18,
      "target_datetime": "2026-04-02 23:00:00",
      "predicted_cmg": 61.5,
      "real_time_offset": 13.7,
      "is_valid_forecast": true,
      "zero_probability": 0.0288,
      "zero_probability_raw": 0.2145,
      "decision_threshold": 0.368,
      "value_prediction": 61.5,
      "confidence_interval": {
        "lower_10th": 37.11,
        "median": 61.5,
        "upper_90th": 80.0
      }
    },
    {
      "horizon": 19,
      "target_datetime": "2026-04-03 00:00:00",
      "predicted_cmg": 56.77,
      "real_time_offset": 14.7,
      "is_valid_forecast": true,
      "zero_probability": 0.1742,
      "zero_probability_raw": 0.325,
      "decision_threshold": 0.3615,
      "value_prediction": 56.77,
      "confidence_interval": {
        "lower_10th": 34.45,
        "median": 56.77,
        "upper_90th": 86.2
      }
    },
    {
      "horizon": 20,
      "target_datetime": "2026-04-03 01:00:00",
      "predicted_cmg": 55.92,
      "real_time_offset": 15.7,
      "is_valid_forecast": true,
      "zero_probability": 0.1954,
      "zero_probability_raw": 0.3341,
      "decision_threshold": 0.3621,
      "value_prediction": 55.92,
      "confidence_interval": {
        "lower_10th": 38.88,
        "median": 55.92,
        "upper_90th": 68.84
      }
    },
    {
      "horizon": 21,
      "target_datetime": "2026-04-03 02:00:00",
      "predicted_cmg": 55.51,
      "real_time_offset": 16.7,
      "is_valid_forecast": true,
      "zero_probability": 0.1235,
      "zero_probability_raw": 0.3008,
      "decision_threshold": 0.3636,
      "value_prediction": 55.51,
      "confidence_interval": {
        "lower_10th": 35.69,
        "median": 55.51,
        "upper_90th": 61.97
      }
    },
    {
      "horizon": 22,
      "target_datetime": "2026-04-03 03:00:00",
      "predicted_cmg": 53.06,
      "real_time_offset": 17.7,
      "is_valid_forecast": true,
      "zero_probability": 0.1409,
      "zero_probability_raw": 0.3116,
      "decision_threshold": 0.3651,
      "value_prediction": 53.06,
      "confidence_interval": {
        "lower_10th": 37.56,
        "median": 53.06,
        "upper_90th": 66.62
      }
    },
    {
      "horizon": 23,
      "target_datetime": "2026-04-03 04:00:00",
      "predicted_cmg": 53.81,
      "real_time_offset": 18.7,
      "is_valid_forecast": true,
      "zero_probability": 0.2593,
      "zero_probability_raw": 0.3629,
      "decision_threshold": 0.3676,
      "value_prediction": 53.81,
      "confidence_interval": {
        "lower_10th": 34.72,
        "median": 53.81,
        "upper_90th": 65.98
      }
    },
    {
      "horizon": 24,
      "target_datetime": "2026-04-03 05:00:00",
      "predicted_cmg": 60.67,
      "real_time_offset": 19.7,
      "is_valid_forecast": true,
      "zero_probability": 0.1338,
      "zero_probability_raw": 0.3122,
      "decision_threshold": 0.3691,
      "value_prediction": 60.67,
      "confidence_interval": {
        "lower_10th": 33.86,
        "median": 60.67,
        "upper_90th": 70.43
      }
    }
  ]
}