{
  "generated_at": "2025-10-13 21:32:59 UTC",
  "base_datetime": "2025-10-13 17:00:00",
  "model_version": "gpu_enhanced_v1",
  "model_performance": {
    "test_mae": 32.43,
    "baseline_mae": 32.2
  },
  "forecasts": [
    {
      "horizon": 1,
      "target_datetime": "2025-10-13 18:00:00",
      "predicted_cmg": 0,
      "zero_probability": 0.7809,
      "zero_probability_raw": 0.5683,
      "decision_threshold": 0.3685,
      "value_prediction": 33.79,
      "confidence_interval": {
        "lower_10th": 13.52,
        "median": 33.79,
        "upper_90th": 64.61
      }
    },
    {
      "horizon": 2,
      "target_datetime": "2025-10-13 19:00:00",
      "predicted_cmg": 0,
      "zero_probability": 0.6802,
      "zero_probability_raw": 0.5269,
      "decision_threshold": 0.3681,
      "value_prediction": 47.96,
      "confidence_interval": {
        "lower_10th": 28.12,
        "median": 47.96,
        "upper_90th": 68.38
      }
    },
    {
      "horizon": 3,
      "target_datetime": "2025-10-13 20:00:00",
      "predicted_cmg": 51.5,
      "zero_probability": 0.1185,
      "zero_probability_raw": 0.3293,
      "decision_threshold": 0.3686,
      "value_prediction": 51.5,
      "confidence_interval": {
        "lower_10th": 26.02,
        "median": 51.5,
        "upper_90th": 67.89
      }
    },
    {
      "horizon": 4,
      "target_datetime": "2025-10-13 21:00:00",
      "predicted_cmg": 61.97,
      "zero_probability": 0.0345,
      "zero_probability_raw": 0.2479,
      "decision_threshold": 0.3682,
      "value_prediction": 61.97,
      "confidence_interval": {
        "lower_10th": 30.96,
        "median": 61.97,
        "upper_90th": 72.65
      }
    },
    {
      "horizon": 5,
      "target_datetime": "2025-10-13 22:00:00",
      "predicted_cmg": 63.0,
      "zero_probability": 0.0096,
      "zero_probability_raw": 0.1824,
      "decision_threshold": 0.368,
      "value_prediction": 63.0,
      "confidence_interval": {
        "lower_10th": 37.22,
        "median": 63.0,
        "upper_90th": 74.76
      }
    },
    {
      "horizon": 6,
      "target_datetime": "2025-10-13 23:00:00",
      "predicted_cmg": 62.79,
      "zero_probability": 0.1956,
      "zero_probability_raw": 0.3613,
      "decision_threshold": 0.368,
      "value_prediction": 62.79,
      "confidence_interval": {
        "lower_10th": 33.01,
        "median": 62.79,
        "upper_90th": 70.86
      }
    },
    {
      "horizon": 7,
      "target_datetime": "2025-10-14 00:00:00",
      "predicted_cmg": 62.86,
      "zero_probability": 0.1976,
      "zero_probability_raw": 0.3614,
      "decision_threshold": 0.3615,
      "value_prediction": 62.86,
      "confidence_interval": {
        "lower_10th": 29.89,
        "median": 62.86,
        "upper_90th": 82.24
      }
    },
    {
      "horizon": 8,
      "target_datetime": "2025-10-14 01:00:00",
      "predicted_cmg": 0,
      "zero_probability": 0.6069,
      "zero_probability_raw": 0.4913,
      "decision_threshold": 0.3621,
      "value_prediction": 52.58,
      "confidence_interval": {
        "lower_10th": 28.7,
        "median": 52.58,
        "upper_90th": 68.48
      }
    },
    {
      "horizon": 9,
      "target_datetime": "2025-10-14 02:00:00",
      "predicted_cmg": 0,
      "zero_probability": 0.6104,
      "zero_probability_raw": 0.4933,
      "decision_threshold": 0.3636,
      "value_prediction": 54.69,
      "confidence_interval": {
        "lower_10th": 23.35,
        "median": 54.69,
        "upper_90th": 66.24
      }
    },
    {
      "horizon": 10,
      "target_datetime": "2025-10-14 03:00:00",
      "predicted_cmg": 0,
      "zero_probability": 0.4457,
      "zero_probability_raw": 0.4468,
      "decision_threshold": 0.3651,
      "value_prediction": 56.99,
      "confidence_interval": {
        "lower_10th": 23.86,
        "median": 56.99,
        "upper_90th": 67.39
      }
    },
    {
      "horizon": 11,
      "target_datetime": "2025-10-14 04:00:00",
      "predicted_cmg": 0,
      "zero_probability": 0.4561,
      "zero_probability_raw": 0.4521,
      "decision_threshold": 0.3676,
      "value_prediction": 52.9,
      "confidence_interval": {
        "lower_10th": 24.23,
        "median": 52.9,
        "upper_90th": 71.39
      }
    },
    {
      "horizon": 12,
      "target_datetime": "2025-10-14 05:00:00",
      "predicted_cmg": 0,
      "zero_probability": 0.8763,
      "zero_probability_raw": 0.608,
      "decision_threshold": 0.3691,
      "value_prediction": 61.83,
      "confidence_interval": {
        "lower_10th": 21.63,
        "median": 61.83,
        "upper_90th": 72.08
      }
    },
    {
      "horizon": 13,
      "target_datetime": "2025-10-14 06:00:00",
      "predicted_cmg": 62.54,
      "zero_probability": 0.3062,
      "zero_probability_raw": 0.4117,
      "decision_threshold": 0.3703,
      "value_prediction": 62.54,
      "confidence_interval": {
        "lower_10th": 27.87,
        "median": 62.54,
        "upper_90th": 69.85
      }
    },
    {
      "horizon": 14,
      "target_datetime": "2025-10-14 07:00:00",
      "predicted_cmg": 0,
      "zero_probability": 0.6663,
      "zero_probability_raw": 0.5231,
      "decision_threshold": 0.3706,
      "value_prediction": 50.9,
      "confidence_interval": {
        "lower_10th": 20.29,
        "median": 50.9,
        "upper_90th": 71.05
      }
    },
    {
      "horizon": 15,
      "target_datetime": "2025-10-14 08:00:00",
      "predicted_cmg": 58.01,
      "zero_probability": 0.2764,
      "zero_probability_raw": 0.4063,
      "decision_threshold": 0.3707,
      "value_prediction": 58.01,
      "confidence_interval": {
        "lower_10th": 15.32,
        "median": 58.01,
        "upper_90th": 91.24
      }
    },
    {
      "horizon": 16,
      "target_datetime": "2025-10-14 09:00:00",
      "predicted_cmg": 0,
      "zero_probability": 0.7232,
      "zero_probability_raw": 0.5465,
      "decision_threshold": 0.3703,
      "value_prediction": 50.3,
      "confidence_interval": {
        "lower_10th": 21.8,
        "median": 50.3,
        "upper_90th": 80.0
      }
    },
    {
      "horizon": 17,
      "target_datetime": "2025-10-14 10:00:00",
      "predicted_cmg": 64.57,
      "zero_probability": 0.3154,
      "zero_probability_raw": 0.422,
      "decision_threshold": 0.3704,
      "value_prediction": 64.57,
      "confidence_interval": {
        "lower_10th": 19.23,
        "median": 64.57,
        "upper_90th": 126.74
      }
    },
    {
      "horizon": 18,
      "target_datetime": "2025-10-14 11:00:00",
      "predicted_cmg": 52.89,
      "zero_probability": 0.2814,
      "zero_probability_raw": 0.4106,
      "decision_threshold": 0.3701,
      "value_prediction": 52.89,
      "confidence_interval": {
        "lower_10th": 25.23,
        "median": 52.89,
        "upper_90th": 133.27
      }
    },
    {
      "horizon": 19,
      "target_datetime": "2025-10-14 12:00:00",
      "predicted_cmg": 0,
      "zero_probability": 0.5287,
      "zero_probability_raw": 0.4853,
      "decision_threshold": 0.3693,
      "value_prediction": 56.98,
      "confidence_interval": {
        "lower_10th": 28.9,
        "median": 56.98,
        "upper_90th": 123.57
      }
    },
    {
      "horizon": 20,
      "target_datetime": "2025-10-14 13:00:00",
      "predicted_cmg": 57.92,
      "zero_probability": 0.3352,
      "zero_probability_raw": 0.4259,
      "decision_threshold": 0.3693,
      "value_prediction": 57.92,
      "confidence_interval": {
        "lower_10th": 26.78,
        "median": 57.92,
        "upper_90th": 124.46
      }
    },
    {
      "horizon": 21,
      "target_datetime": "2025-10-14 14:00:00",
      "predicted_cmg": 0,
      "zero_probability": 0.4101,
      "zero_probability_raw": 0.4462,
      "decision_threshold": 0.3695,
      "value_prediction": 62.23,
      "confidence_interval": {
        "lower_10th": 27.18,
        "median": 62.23,
        "upper_90th": 114.92
      }
    },
    {
      "horizon": 22,
      "target_datetime": "2025-10-14 15:00:00",
      "predicted_cmg": 0,
      "zero_probability": 0.4982,
      "zero_probability_raw": 0.4685,
      "decision_threshold": 0.3695,
      "value_prediction": 68.88,
      "confidence_interval": {
        "lower_10th": 23.59,
        "median": 68.88,
        "upper_90th": 122.65
      }
    },
    {
      "horizon": 23,
      "target_datetime": "2025-10-14 16:00:00",
      "predicted_cmg": 0,
      "zero_probability": 0.6018,
      "zero_probability_raw": 0.495,
      "decision_threshold": 0.3694,
      "value_prediction": 57.28,
      "confidence_interval": {
        "lower_10th": 27.08,
        "median": 57.28,
        "upper_90th": 120.08
      }
    },
    {
      "horizon": 24,
      "target_datetime": "2025-10-14 17:00:00",
      "predicted_cmg": 0,
      "zero_probability": 0.623,
      "zero_probability_raw": 0.4971,
      "decision_threshold": 0.3688,
      "value_prediction": 48.49,
      "confidence_interval": {
        "lower_10th": 21.22,
        "median": 48.49,
        "upper_90th": 119.82
      }
    }
  ]
}